PyNFVSDK/__init__.py
PyNFVSDK-0.1.dev8.dist-info/LICENSE.txt
PyNFVSDK-0.1.dev8.dist-info/METADATA
PyNFVSDK-0.1.dev8.dist-info/WHEEL
PyNFVSDK-0.1.dev8.dist-info/top_level.txt
PyNFVSDK-0.1.dev8.dist-info/RECORD
